dsd_codered/__init__.py
dsd_codered/deploy.py
dsd_codered/deploy_messages.py
dsd_codered/platform_deployer.py
dsd_codered/plugin_config.py
dsd_codered/utils.py
dsd_codered/templates/dockerfile_example
dsd_codered/templates/settings.py
dsd_codered/templates/settings_prod.py
dsd_codered-0.2.0.dist-info/LICENSE
dsd_codered-0.2.0.dist-info/METADATA
dsd_codered-0.2.0.dist-info/WHEEL
dsd_codered-0.2.0.dist-info/top_level.txt
dsd_codered-0.2.0.dist-info/RECORD
